easy_test.py
easy_automation/__init__.py
easy_automation/contrib/__init__.py
easy_automation/contrib/after_error_hook.py
easy_automation/contrib/appium_mixin.py
easy_automation/contrib/before_click_hook.py
easy_automation/contrib/easy_assert_mixin.py
easy_automation/contrib/elements.py
easy_automation/contrib/selenium_mixin.py
easy_automation/contrib/page/__init__.py
easy_automation/contrib/page/appium_page.py
easy_automation/contrib/page/page.py
easy_automation/contrib/page/selenium_page.py
easy_automation/core/__init__.py
easy_automation/core/base_appium.py
easy_automation/core/base_page.py
easy_automation/core/base_request.py
easy_automation/core/manage.py
easy_automation/core/plugin.py
easy_automation/core/template_command.py
easy_automation/report/__init__.py
easy_automation/report/listener.py
easy_automation/report/logger.py
easy_automation/report/model.py
easy_automation/report/reporter.py
easy_automation/report/types.py
easy_automation/report/utils.py
easy_automation/service/__init__.py
easy_automation/service/cases.py
easy_automation/service/consul_client.py
easy_automation/service/health.py
easy_automation/templates/api_template/__init__.py-tpl
easy_automation/templates/api_template/project_api/__init__.py-tpl
easy_automation/templates/api_template/project_api/project_api.py-tpl
easy_automation/templates/api_template/testcases/__init__.py-tpl
easy_automation/templates/api_template/testcases/conftest.py-tpl
easy_automation/templates/api_template/testdata/testdata.yaml
easy_automation/templates/proj_template/config.py-tpl
easy_automation/templates/proj_template/conftest.py-tpl
easy_automation/templates/proj_template/manage.py-tpl
easy_automation/templates/proj_template/settings/__init__.py-tpl
easy_automation/templates/proj_template/settings/settings.py-tpl
easy_automation/templates/proj_template/settings/k8s/pre
easy_automation/templates/web_template/__init__.py-tpl
easy_automation/templates/web_template/project_page/__init__.py-tpl
easy_automation_test-0.0.8.5.dist-info/LICENSE
easy_automation_test-0.0.8.5.dist-info/METADATA
easy_automation_test-0.0.8.5.dist-info/WHEEL
easy_automation_test-0.0.8.5.dist-info/entry_points.txt
easy_automation_test-0.0.8.5.dist-info/top_level.txt
easy_automation_test-0.0.8.5.dist-info/RECORD
