Metadata-Version: 2.1
Name: easy_automation_test
Version: 0.0.8.5
Summary: Easy to create a web or api automation test project
Home-page: https://github.com/zhangjiapeng23/easy_automation_test
Author: jameszhang
Author-email: 18373230129@163.com
Project-URL: Bug Tracker, https://github.com/zhangjiapeng23/easy_automation_test/issues
Keywords: automation test,web,api
Classifier: Programming Language :: Python :: 3
Classifier: License :: OSI Approved :: MIT License
Classifier: Operating System :: OS Independent
Requires-Python: >=3.9
License-File: LICENSE
Requires-Dist: allure-pytest>=2.12.0
Requires-Dist: allure-python-commons>=2.12.0
Requires-Dist: async-generator>=1.10
Requires-Dist: async-timeout>=4.0.2
Requires-Dist: atomicwrites>=1.4.0
Requires-Dist: attrs>=21.2.0
Requires-Dist: bleach>=3.3.1
Requires-Dist: blinker>=1.7.0
Requires-Dist: build>=0.5.1
Requires-Dist: cachetools>=5.3.0
Requires-Dist: certifi>=2021.5.30
Requires-Dist: cffi>=1.15.0
Requires-Dist: charset-normalizer>=2.0.3
Requires-Dist: click>=8.1.7
Requires-Dist: colorama>=0.4.4
Requires-Dist: cryptography>=36.0.2
Requires-Dist: docutils>=0.17.1
Requires-Dist: exceptiongroup>=1.1.0
Requires-Dist: Faker>=8.11.0
Requires-Dist: flask>=3.0.2
Requires-Dist: google-auth>=2.16.0
Requires-Dist: gunicorn>=23.0.0
Requires-Dist: h11>=0.13.0
Requires-Dist: idna>=3.2
Requires-Dist: importlib-metadata>=4.6.1
Requires-Dist: iniconfig>=1.1.1
Requires-Dist: itsdangerous>=2.1.2
Requires-Dist: Jinja2>=3.1.3
Requires-Dist: keyring>=23.0.1
Requires-Dist: kubernetes>=25.3.0
Requires-Dist: MarkupSafe>=2.1.5
Requires-Dist: oauthlib>=3.2.2
Requires-Dist: outcome>=1.1.0
Requires-Dist: packaging>=21.0
Requires-Dist: pep517>=0.11.0
Requires-Dist: pkginfo>=1.7.1
Requires-Dist: pluggy>=0.13.1
Requires-Dist: py>=1.10.0
Requires-Dist: pyasn1>=0.4.8
Requires-Dist: pyasn1-modules>=0.2.8
Requires-Dist: pycparser>=2.21
Requires-Dist: Pygments>=2.9.0
Requires-Dist: PyMySQL>=1.0.2
Requires-Dist: pyOpenSSL>=22.0.0
Requires-Dist: pyparsing>=2.4.7
Requires-Dist: PySocks>=1.7.1
Requires-Dist: pytest>=6.2.4
Requires-Dist: python-dateutil>=2.8.2
Requires-Dist: pywin32-ctypes>=0.2.0
Requires-Dist: PyYAML>=5.4.1
Requires-Dist: py-consul>=1.5.1
Requires-Dist: readme-renderer>=29.0
Requires-Dist: redis>=4.5.1
Requires-Dist: requests>=2.26.0
Requires-Dist: requests-oauthlib>=1.3.1
Requires-Dist: requests-toolbelt>=0.9.1
Requires-Dist: rfc3986>=1.5.0
Requires-Dist: rsa>=4.9
Requires-Dist: selenium>=4.8.0
Requires-Dist: six>=1.16.0
Requires-Dist: sniffio>=1.2.0
Requires-Dist: sortedcontainers>=2.4.0
Requires-Dist: text-unidecode>=1.3
Requires-Dist: toml>=0.10.2
Requires-Dist: tomli>=1.0.4
Requires-Dist: tqdm>=4.61.2
Requires-Dist: trio>=0.20.0
Requires-Dist: trio-websocket>=0.9.2
Requires-Dist: twine>=3.4.2
Requires-Dist: urllib3>=1.26.6
Requires-Dist: urllib3-secure-extra>=0.1.0
Requires-Dist: waitress>=3.0.0
Requires-Dist: webencodings>=0.5.1
Requires-Dist: websocket-client>=1.5.1
Requires-Dist: werkzeug>=3.0.1
Requires-Dist: wsproto>=1.1.0
Requires-Dist: zipp>=3.5.0
